cursor_utils/__init__.py
cursor_utils/main.py
cursor_utils/py.typed
cursor_utils/version.py
cursor_utils/cli/__init__.py
cursor_utils/cli/parser.py
cursor_utils/cli/commands/__init__.py
cursor_utils/cli/commands/config.py
cursor_utils/cli/commands/gemini.py
cursor_utils/cli/commands/github.py
cursor_utils/cli/commands/install.py
cursor_utils/cli/commands/project.py
cursor_utils/cli/commands/repo.py
cursor_utils/cli/commands/update.py
cursor_utils/cli/commands/web.py
cursor_utils/core/__init__.py
cursor_utils/core/config.py
cursor_utils/core/errors.py
cursor_utils/core/output.py
cursor_utils/models/cursor-utils.md
cursor_utils/models/cursor-utils.mdc
cursor_utils/services/__init__.py
cursor_utils/services/gemini.py
cursor_utils/services/github.py
cursor_utils/services/perplexity.py
cursor_utils/services/updater.py
cursor_utils/utils/__init__.py
cursor_utils/utils/file_rank_algo.py
cursor_utils/utils/fs.py
cursor_utils/utils/git.py
cursor_utils/utils/text.py
cursor_utils-0.1.5.dist-info/METADATA
cursor_utils-0.1.5.dist-info/WHEEL
cursor_utils-0.1.5.dist-info/entry_points.txt
cursor_utils-0.1.5.dist-info/licenses/LICENSE
cursor_utils-0.1.5.dist-info/RECORD
