Metadata-Version: 2.4
Name: cursor-utils
Version: 0.1.5
Summary: Give your Cursor IDE Agents superpowers.
Project-URL: Homepage, https://github.com/gweidart/cursor-utils
Project-URL: Documentation, https://gweidart.github.io/cursor-utils/
Project-URL: Repository, https://github.com/gweidart/cursor-utils
Project-URL: Issues, https://github.com/gweidart/cursor-utils/issues
Project-URL: Changelog, https://github.com/gweidart/cursor-utils/blob/main/CHANGELOG.md
Author-email: gweidart <gweidart@gmail.com>
License: MIT
License-File: LICENSE
Keywords: agent,agentic,agentic programming,agentic programming with python,agentic programming with python 3,agentic programming with python 3.10,agentic programming with python 3.11,agentic programming with python 3.12,ai,anthropic,chatgpt,claude,cli,cursor,cursor ide,cursor-tools,cursor-utils,gemini,google,gpt,gpt-3.5-turbo,gpt-3.5-turbo-0125,gpt-4,gpt-4o,gpt-4o-mini,gpt-o1,openai,python,python3,sonnet-3.7,tools,utils
Classifier: Development Status :: 3 - Alpha
Classifier: Intended Audience :: Developers
Classifier: License :: OSI Approved :: MIT License
Classifier: Programming Language :: Python :: 3
Classifier: Programming Language :: Python :: 3.10
Classifier: Programming Language :: Python :: 3.11
Classifier: Programming Language :: Python :: 3.12
Classifier: Programming Language :: Python :: Implementation :: CPython
Classifier: Programming Language :: Python :: Implementation :: PyPy
Classifier: Typing :: Typed
Requires-Python: >=3.10
Requires-Dist: bump-my-version
Requires-Dist: httpx
Requires-Dist: packaging
Requires-Dist: pathspec
Requires-Dist: requests
Requires-Dist: rich
Requires-Dist: rich-click
Provides-Extra: dev
Requires-Dist: black; extra == 'dev'
Requires-Dist: isort; extra == 'dev'
Requires-Dist: mkdocs; extra == 'dev'
Requires-Dist: mypy; extra == 'dev'
Requires-Dist: pyright; extra == 'dev'
Requires-Dist: pytest; extra == 'dev'
Requires-Dist: ruff; extra == 'dev'
Provides-Extra: test
